{"version":"1.0","chainId":"31","createdAt":1696799506756,"meta":{"name":"Unpause RSK Mainnet marginTrade iDLLR Lending Pool","description":"","txBuilderVersion":"1.16.1","createdFromSafeAddress":"0xE79232Db7d096e781647405B28398121AEA08536","createdFromOwnerAddress":"","checksum":"0xb7b9e6705bc5085a6ba2ca2e506e7d947c38dc1ccc15f19971d793b5922ce5e6"},"transactions":[{"to":"0x077FCB01cAb070a30bC14b44559C96F529eE017F","value":"0","data":null,"contractMethod":{"inputs":[{"internalType":"string","name":"funcId","type":"string"},{"internalType":"bool","name":"isPaused","type":"bool"}],"name":"toggleFunctionPause","payable":false},"contractInputsValues":{"funcId":"marginTrade(bytes32,uint256,uint256,uint256,address,address,uint256,bytes)","isPaused":"false"}}]}